README.md
setup.py
yogpt/cli.py
yogpt/g4f.py
yogpt.egg-info/PKG-INFO
yogpt.egg-info/SOURCES.txt
yogpt.egg-info/dependency_links.txt
yogpt.egg-info/entry_points.txt
yogpt.egg-info/requires.txt
yogpt.egg-info/top_level.txt