Metadata-Version: 2.1
Name: yogpt
Version: 0.0.2
Summary: Command-line interface for GPT-like LLMs
Home-page: https://github.com/shwars/yogpt
Author: Dmitri Soshnikov
Author-email: dmitri@soshnikov.com
License: MIT license
Classifier: Programming Language :: Python :: 3
Classifier: Intended Audience :: Developers
Classifier: License :: OSI Approved :: MIT License
Classifier: Operating System :: OS Independent
Classifier: Topic :: Software Development
Requires-Dist: requests
Requires-Dist: langchain
Requires-Dist: g4f
